ROSCO_testing/ROSCO_testing.py
ROSCO_testing/__init__.py
ROSCO_testing/run_Testing.py
ROSCO_toolbox/__init__.py
ROSCO_toolbox/control_interface.py
ROSCO_toolbox/controller.py
ROSCO_toolbox/sim.py
ROSCO_toolbox/turbine.py
ROSCO_toolbox/utilities.py
ROSCO_toolbox/ofTools/__init__.py
ROSCO_toolbox/ofTools/case_gen/CaseGen_General.py
ROSCO_toolbox/ofTools/case_gen/CaseGen_IEC.py
ROSCO_toolbox/ofTools/case_gen/__init__.py
ROSCO_toolbox/ofTools/case_gen/runFAST_pywrapper.py
ROSCO_toolbox/ofTools/fast_io/FAST_post.py
ROSCO_toolbox/ofTools/fast_io/FAST_reader.py
ROSCO_toolbox/ofTools/fast_io/FAST_vars.py
ROSCO_toolbox/ofTools/fast_io/FAST_vars_out.py
ROSCO_toolbox/ofTools/fast_io/FAST_wrapper.py
ROSCO_toolbox/ofTools/fast_io/FAST_writer.py
ROSCO_toolbox/ofTools/fast_io/__init__.py
ROSCO_toolbox/ofTools/fast_io/file.py
ROSCO_toolbox/ofTools/fast_io/output_processing.py
ROSCO_toolbox/ofTools/fast_io/pyIECWind.py
ROSCO_toolbox/ofTools/fast_io/read_fast_input.py
ROSCO_toolbox/ofTools/fast_io/turbsim_io/__init__.py
ROSCO_toolbox/ofTools/fast_io/turbsim_io/turbsim_reader.py
ROSCO_toolbox/ofTools/fast_io/turbsim_io/turbsim_vartrees.py
ROSCO_toolbox/ofTools/fast_io/turbsim_io/turbsim_wrapper.py
ROSCO_toolbox/ofTools/fast_io/turbsim_io/turbsim_writer.py
ROSCO_toolbox/ofTools/fast_io/turbsim_io/turbulence_spectrum.py
ROSCO_toolbox/ofTools/fast_io/turbsim_io/wind_profile_writer.py
ROSCO_toolbox/ofTools/util/FileTools.py
ROSCO_toolbox/ofTools/util/__init__.py
ROSCO_toolbox/ofTools/util/spectral.py
rosco_toolbox-2.3.0.dist-info/LICENSE
rosco_toolbox-2.3.0.dist-info/METADATA
rosco_toolbox-2.3.0.dist-info/WHEEL
rosco_toolbox-2.3.0.dist-info/top_level.txt
rosco_toolbox-2.3.0.dist-info/RECORD
