Metadata-Version: 2.1
Name: rosco-toolbox
Version: 2.3.0
Summary: A toolbox for development of wind turbine controllers.
Home-page: https://github.com/NREL/ROSCO_toolbox
Author: NREL National Wind Technology Center
Author-email: nikhar.abbas@nrel.gov
License: Apache License, Version 2.0
Platform: UNKNOWN
Requires-Python: >=3.4
Requires-Dist: matplotlib
Requires-Dist: numpy
Requires-Dist: pytest
Requires-Dist: scipy
Requires-Dist: pyYAML
Requires-Dist: future
Requires-Dist: pandas
Provides-Extra: docs
Requires-Dist: Sphinx (>=2.0) ; extra == 'docs'
Requires-Dist: sphinxcontrib-napoleon (>=0.7) ; extra == 'docs'
Requires-Dist: readthedocs-sphinx-ext (>=0.5.15) ; extra == 'docs'
